iview/__init__.py
iview-0.24.dist-info/DESCRIPTION.rst
iview-0.24.dist-info/METADATA
iview-0.24.dist-info/metadata.json
iview-0.24.dist-info/RECORD
iview-0.24.dist-info/top_level.txt
iview-0.24.dist-info/WHEEL
