Metadata-Version: 2.0
Name: iview
Version: 0.24
Summary: Automatically download new episodes of your favourite series from ABC iView.
Home-page: UNKNOWN
Author: ABC iView
Author-email: abcauto@tsjh28.bid
License: MIT
Platform: UNKNOWN
Requires-Dist: youtube-dl
Requires-Dist: requests
